<?xml version="1.0" encoding="utf-8"?>
<Lines>
  <Line>
    <Area>Center</Area>
    <ID>0</ID>
    <LineNumber>286</LineNumber>
    <FirstStation>63946</FirstStation>
    <LastStation>23013</LastStation>
    <IsActive>True</IsActive>
  </Line>
  <Line>
    <Area>Center</Area>
    <ID>1</ID>
    <LineNumber>286</LineNumber>
    <FirstStation>22955</FirstStation>
    <LastStation>63275</LastStation>
    <IsActive>True</IsActive>
  </Line>
  <Line>
    <Area>Center</Area>
    <ID>2</ID>
    <LineNumber>95</LineNumber>
    <FirstStation>63946</FirstStation>
    <LastStation>32488</LastStation>
    <IsActive>True</IsActive>
  </Line>
  <Line>
    <Area>Center</Area>
    <ID>3</ID>
    <LineNumber>95</LineNumber>
    <FirstStation>34934</FirstStation>
    <LastStation>63275</LastStation>
    <IsActive>True</IsActive>
  </Line>
  <Line>
    <Area>Center</Area>
    <ID>4</ID>
    <LineNumber>70</LineNumber>
    <FirstStation>38160</FirstStation>
    <LastStation>23013</LastStation>
    <IsActive>True</IsActive>
  </Line>
  <Line>
    <Area>Center</Area>
    <ID>5</ID>
    <LineNumber>947</LineNumber>
    <FirstStation>41700</FirstStation>
    <LastStation>42657</LastStation>
    <IsActive>True</IsActive>
  </Line>
  <Line>
    <Area>Center</Area>
    <ID>6</ID>
    <LineNumber>947</LineNumber>
    <FirstStation>42658</FirstStation>
    <LastStation>61090</LastStation>
    <IsActive>True</IsActive>
  </Line>
  <Line>
    <Area>Center</Area>
    <ID>7</ID>
    <LineNumber>250</LineNumber>
    <FirstStation>20001</FirstStation>
    <LastStation>32695</LastStation>
    <IsActive>True</IsActive>
  </Line>
  <Line>
    <Area>Center</Area>
    <ID>8</ID>
    <LineNumber>250</LineNumber>
    <FirstStation>35368</FirstStation>
    <LastStation>27997</LastStation>
    <IsActive>True</IsActive>
  </Line>
  <Line>
    <Area>Center</Area>
    <ID>9</ID>
    <LineNumber>20</LineNumber>
    <FirstStation>32296</FirstStation>
    <LastStation>26643</LastStation>
    <IsActive>True</IsActive>
  </Line>
  <Line>
    <Area>Center</Area>
    <ID>10</ID>
    <LineNumber>20</LineNumber>
    <FirstStation>26643</FirstStation>
    <LastStation>36667</LastStation>
    <IsActive>True</IsActive>
  </Line>
  <Line>
    <Area>Center</Area>
    <ID>11</ID>
    <LineNumber>82</LineNumber>
    <FirstStation>36667</FirstStation>
    <LastStation>26956</LastStation>
    <IsActive>True</IsActive>
  </Line>
  <Line>
    <Area>Center</Area>
    <ID>12</ID>
    <LineNumber>82</LineNumber>
    <FirstStation>26959</FirstStation>
    <LastStation>36667</LastStation>
    <IsActive>True</IsActive>
  </Line>
</Lines>